cfg/__init__.py
cfg/__main__.py
cfg/__version__.py
cfg/_logging.py
cfg/data.py
cfg/errors.py
cfg/file.py
cfg2-0.2b0.data/data/LICENSE.txt
cfg2-0.2b0.data/data/requirements.txt
cfg2-0.2b0.dist-info/LICENSE.txt
cfg2-0.2b0.dist-info/METADATA
cfg2-0.2b0.dist-info/WHEEL
cfg2-0.2b0.dist-info/entry_points.txt
cfg2-0.2b0.dist-info/top_level.txt
cfg2-0.2b0.dist-info/RECORD
