Metadata-Version: 2.1
Name: cfg2
Version: 0.2b0
Summary: Python package generated from template https://framagit.org/1ohmatr/sw/py/template
Home-page: https://framagit.org/1ohmatr/sw/py/cfg2
Author: neze
Author-email: neze@melix.org
License: UNKNOWN
Platform: UNKNOWN
Classifier: Programming Language :: Python :: 3
Classifier: License :: OSI Approved :: MIT License
Requires-Dist: pathlib2
Requires-Dist: PyYAML
